{
"autoplayBgm":false,"autoplayBgs":false,"battleback1Name":"","battleback2Name":"","bgm":{"name":"","pan":0,"pitch":100,"volume":90},"bgs":{"name":"","pan":0,"pitch":100,"volume":90},"disableDashing":false,"displayName":"3号楼内-教室B","encounterList":[],"encounterStep":30,"height":8,"note":"","parallaxLoopX":false,"parallaxLoopY":false,"parallaxName":"","parallaxShow":true,"parallaxSx":0,"parallaxSy":0,"scrollType":0,"specifyBattleback":false,"tilesetId":6,"width":13,
"data":[7139,7138,7138,7138,7138,7138,7138,7138,7138,7142,4108,7143,7142,7141,7145,7144,7144,7144,7144,7144,7144,7144,7148,1570,7149,7140,7141,1570,1570,1570,1570,1570,1570,1570,1570,1570,1570,1570,7141,7141,1570,1570,1570,1570,1570,1570,1570,1570,1570,1570,1570,7141,7141,1570,1570,1570,1570,1570,1570,1570,1570,1570,1570,1570,7141,7141,1570,1570,1570,1570,1570,1570,1570,1570,1570,1570,1570,7141,7141,1570,1570,1570,1570,1570,1570,1570,1570,1570,1570,1570,7141,7145,7147,7146,7146,7146,7146,7146,7146,7146,7146,7146,7150,7149,0,0,0,0,0,0,0,0,0,0,0,0,0,0,0,0,0,0,0,0,0,0,0,0,0,0,0,0,0,0,0,0,0,0,0,0,0,0,0,0,0,0,0,0,0,0,0,0,0,0,0,0,0,0,0,0,0,0,0,0,0,0,0,0,0,0,0,0,0,0,0,0,0,0,0,0,0,0,0,0,0,0,0,0,0,0,0,0,0,0,0,0,0,0,0,0,0,0,0,0,0,0,0,0,0,0,0,0,0,0,0,0,0,0,0,0,0,0,0,0,0,0,0,0,0,0,0,0,0,0,0,0,0,0,0,0,0,0,0,0,0,0,0,0,127,0,0,0,0,0,0,0,0,0,0,0,0,0,0,0,0,0,0,0,0,0,0,0,0,0,0,0,0,127,0,0,0,0,0,0,0,0,0,0,0,0,0,0,0,0,0,0,0,0,0,0,0,0,0,0,0,0,0,0,0,0,0,0,0,0,256,257,257,257,258,0,0,0,0,0,0,0,0,264,265,265,265,266,0,143,300,0,0,0,0,0,0,0,0,0,0,0,0,0,0,0,0,0,433,0,127,0,127,0,127,0,127,0,0,0,0,145,0,0,0,147,0,145,145,0,0,0,0,0,0,127,0,433,0,0,0,127,0,127,0,0,0,0,145,0,145,0,0,0,145,146,0,0,0,0,0,0,0,0,0,0,0,0,0,0,0,0,0,0,0,0,0,0,0,0,0,0,0,0,0,0,0,0,0,0,0,0,0,0,0,5,0,0,0,5,0,0,0,0,0,0,0,0,0,0,0,0,5,0,0,0,0,0,0,0,0,0,0,0,0,5,0,0,0,0,0,0,0,0,0,0,0,0,5,0,0,0,0,0,0,0,0,0,0,0,0,5,0,0,0,0,0,0,0,0,0,0,0,0,0,0,0,0,0,0,0,0,0,0,0,0,0,0,0,0,0,0,0,0,0,0,0,0,0,0,0,0,0,0,0,0,0,0,0,0,0,0,0,0,0,0,0,0,0,0,0,0,0,0,0,0,0,0,0,0,0,0,0,0,0,0,0,0,0,0,0,0,0,0,0,0,0,0,0,0,0,0,0,0,0,0,0,0,0,0,0,0,0,0,0,0,0,0,0,0,0,0,0,0,0,0,0,0,0,0,0,0,0,0,0,0,0,0,0,0],
"events":[
null,
{"id":1,"name":"EV001","note":"","pages":[{"conditions":{"actorId":1,"actorValid":false,"itemId":1,"itemValid":false,"selfSwitchCh":"A","selfSwitchValid":false,"switch1Id":1,"switch1Valid":false,"switch2Id":1,"switch2Valid":false,"variableId":1,"variableValid":false,"variableValue":0},"directionFix":false,"image":{"characterIndex":0,"characterName":"","direction":2,"pattern":0,"tileId":0},"list":[{"code":250,"indent":0,"parameters":[{"name":"Move1","pan":0,"pitch":100,"volume":90}]},{"code":201,"indent":0,"parameters":[0,18,12,5,0,0]},{"code":0,"indent":0,"parameters":[]}],"moveFrequency":3,"moveRoute":{"list":[{"code":0,"parameters":[]}],"repeat":true,"skippable":false,"wait":false},"moveSpeed":3,"moveType":0,"priorityType":0,"stepAnime":false,"through":false,"trigger":1,"walkAnime":true}],"x":10,"y":0},
{"id":2,"name":"EV002","note":"","pages":[{"conditions":{"actorId":1,"actorValid":false,"itemId":1,"itemValid":false,"selfSwitchCh":"A","selfSwitchValid":false,"switch1Id":1,"switch1Valid":false,"switch2Id":1,"switch2Valid":false,"variableId":1,"variableValid":false,"variableValue":0},"directionFix":false,"image":{"tileId":130,"characterName":"","characterIndex":0,"direction":2,"pattern":0},"list":[{"code":101,"indent":0,"parameters":["",0,1,2]},{"code":401,"indent":0,"parameters":["这是一台笔记本电脑，不合时宜地出现在了高中生教室里，"]},{"code":401,"indent":0,"parameters":["应该是某位老师的所有物，但我应该先去找人问问。"]},{"code":0,"indent":0,"parameters":[]}],"moveFrequency":3,"moveRoute":{"list":[{"code":0,"parameters":[]}],"repeat":true,"skippable":false,"wait":false},"moveSpeed":3,"moveType":0,"priorityType":1,"stepAnime":false,"through":false,"trigger":0,"walkAnime":true},{"conditions":{"actorId":1,"actorValid":false,"itemId":1,"itemValid":false,"selfSwitchCh":"A","selfSwitchValid":false,"switch1Id":5,"switch1Valid":true,"switch2Id":1,"switch2Valid":false,"variableId":1,"variableValid":false,"variableValue":0},"directionFix":false,"image":{"tileId":130,"characterName":"","characterIndex":0,"direction":2,"pattern":0},"list":[{"code":111,"indent":0,"parameters":[0,4,0]},{"code":101,"indent":1,"parameters":["",0,1,2]},{"code":401,"indent":1,"parameters":["我应该先去接电话。"]},{"code":0,"indent":1,"parameters":[]},{"code":411,"indent":0,"parameters":[]},{"code":111,"indent":1,"parameters":[2,"B",1]},{"code":111,"indent":2,"parameters":[2,"A",1]},{"code":101,"indent":3,"parameters":["",0,1,2]},{"code":401,"indent":3,"parameters":["这台笔记本电脑应该就是贾老师的了。"]},{"code":101,"indent":3,"parameters":["",0,1,2]},{"code":401,"indent":3,"parameters":["想要打开它似乎需要密码。"]},{"code":123,"indent":3,"parameters":["A",0]},{"code":0,"indent":3,"parameters":[]},{"code":411,"indent":2,"parameters":[]},{"code":101,"indent":3,"parameters":["",0,1,2]},{"code":401,"indent":3,"parameters":["请输入密码："]},{"code":401,"indent":3,"parameters":["（密码需要一位一位调整，不能直接输入数字）"]},{"code":0,"indent":3,"parameters":[]},{"code":412,"indent":2,"parameters":[]},{"code":103,"indent":2,"parameters":[1,4]},{"code":111,"indent":2,"parameters":[1,1,0,2569,0]},{"code":250,"indent":3,"parameters":[{"name":"Computer","volume":30,"pitch":100,"pan":0}]},{"code":101,"indent":3,"parameters":["",0,1,2]},{"code":401,"indent":3,"parameters":["密码正确，正在启动。"]},{"code":101,"indent":3,"parameters":["",0,1,2]},{"code":401,"indent":3,"parameters":["随着电脑发出的光，我注意到，键盘上沾着不少已经干掉"]},{"code":401,"indent":3,"parameters":["的暗红色斑点。"]},{"code":101,"indent":3,"parameters":["",0,1,2]},{"code":401,"indent":3,"parameters":["开机之后，电脑就卡住了，只剩下一个电子邮件的界面。"]},{"code":101,"indent":3,"parameters":["",0,1,2]},{"code":401,"indent":3,"parameters":["有四封邮件可以阅读，要读吗？"]},{"code":118,"indent":3,"parameters":["100"]},{"code":102,"indent":3,"parameters":[["第一封","第二封","第三封","第四封","不看了"],4,-1,2,0]},{"code":402,"indent":3,"parameters":[0,"第一封"]},{"code":101,"indent":4,"parameters":["",0,1,2]},{"code":401,"indent":4,"parameters":["贾洁："]},{"code":401,"indent":4,"parameters":["已经没有什么好说的了，祝你幸福。"]},{"code":401,"indent":4,"parameters":[""]},{"code":401,"indent":4,"parameters":["柯"]},{"code":119,"indent":4,"parameters":["100"]},{"code":0,"indent":4,"parameters":[]},{"code":402,"indent":3,"parameters":[1,"第二封"]},{"code":101,"indent":4,"parameters":["",0,1,2]},{"code":401,"indent":4,"parameters":["【私密邮件】贾老师："]},{"code":401,"indent":4,"parameters":["你不能以私报公！而且明栎的事也不全是我的错，我确实是"]},{"code":401,"indent":4,"parameters":["她的班主任，但是这本身就是一个家庭学校共同的问题。"]},{"code":401,"indent":4,"parameters":["我们理解您的心情，发生这种事谁都不想的。"]},{"code":111,"indent":4,"parameters":[2,"C",1]},{"code":101,"indent":5,"parameters":["",0,1,2]},{"code":401,"indent":5,"parameters":["明栎（yue）？难道是贾明栎？好像是贾洁老师的女儿，我"]},{"code":401,"indent":5,"parameters":["上学时邻班的女孩，说起来好像跟刚刚见到的女生有几分"]},{"code":401,"indent":5,"parameters":["相似。"]},{"code":101,"indent":5,"parameters":["",0,1,2]},{"code":401,"indent":5,"parameters":["但她在高三寒假之前突然转学离开了，在这样的时间点转学"]},{"code":401,"indent":5,"parameters":["还真是少见。"]},{"code":123,"indent":5,"parameters":["C",0]},{"code":0,"indent":5,"parameters":[]},{"code":412,"indent":4,"parameters":[]},{"code":119,"indent":4,"parameters":["100"]},{"code":0,"indent":4,"parameters":[]},{"code":402,"indent":3,"parameters":[2,"第三封"]},{"code":101,"indent":4,"parameters":["",0,1,2]},{"code":401,"indent":4,"parameters":["贾老师："]},{"code":401,"indent":4,"parameters":["市教育局已经批准了您女儿的转校申请，祝她在新的学校"]},{"code":401,"indent":4,"parameters":["学习顺利！"]},{"code":401,"indent":4,"parameters":["祝好，市教育局李老师"]},{"code":119,"indent":4,"parameters":["100"]},{"code":0,"indent":4,"parameters":[]},{"code":402,"indent":3,"parameters":[3,"第四封"]},{"code":101,"indent":4,"parameters":["",0,1,2]},{"code":401,"indent":4,"parameters":["这封邮件似乎并不是发给贾老师的，没有任何署名："]},{"code":401,"indent":4,"parameters":[""]},{"code":401,"indent":4,"parameters":["愿作辰星伴明月，散尔心边一拢黑。"]},{"code":401,"indent":4,"parameters":["梦假情真超凡境，可怜莎翁笔下人。"]},{"code":119,"indent":4,"parameters":["100"]},{"code":0,"indent":4,"parameters":[]},{"code":402,"indent":3,"parameters":[4,"不看了"]},{"code":111,"indent":4,"parameters":[2,"D",1]},{"code":250,"indent":5,"parameters":[{"name":"Phone","volume":90,"pitch":100,"pan":0}]},{"code":230,"indent":5,"parameters":[90]},{"code":250,"indent":5,"parameters":[{"name":"Phone","volume":90,"pitch":100,"pan":0}]},{"code":101,"indent":5,"parameters":["",0,1,2]},{"code":401,"indent":5,"parameters":["电话又一次响了起来。"]},{"code":121,"indent":5,"parameters":[4,4,0]},{"code":123,"indent":5,"parameters":["D",0]},{"code":122,"indent":5,"parameters":[20,20,0,0,2]},{"code":0,"indent":5,"parameters":[]},{"code":412,"indent":4,"parameters":[]},{"code":0,"indent":4,"parameters":[]},{"code":404,"indent":3,"parameters":[]},{"code":123,"indent":3,"parameters":["B",0]},{"code":0,"indent":3,"parameters":[]},{"code":411,"indent":2,"parameters":[]},{"code":250,"indent":3,"parameters":[{"name":"Cursor1","volume":60,"pitch":100,"pan":0}]},{"code":101,"indent":3,"parameters":["",0,1,2]},{"code":401,"indent":3,"parameters":["密码错误！"]},{"code":0,"indent":3,"parameters":[]},{"code":412,"indent":2,"parameters":[]},{"code":0,"indent":2,"parameters":[]},{"code":411,"indent":1,"parameters":[]},{"code":101,"indent":2,"parameters":["",0,1,2]},{"code":401,"indent":2,"parameters":["电脑已经开机了，屏幕上还是那些电子邮件，要看哪一封？"]},{"code":119,"indent":2,"parameters":["100"]},{"code":0,"indent":2,"parameters":[]},{"code":412,"indent":1,"parameters":[]},{"code":0,"indent":1,"parameters":[]},{"code":412,"indent":0,"parameters":[]},{"code":0,"indent":0,"parameters":[]}],"moveFrequency":3,"moveRoute":{"list":[{"code":0,"parameters":[]}],"repeat":true,"skippable":false,"wait":false},"moveSpeed":3,"moveType":0,"priorityType":1,"stepAnime":false,"through":false,"trigger":0,"walkAnime":true},{"conditions":{"actorId":1,"actorValid":false,"itemId":1,"itemValid":false,"selfSwitchCh":"A","selfSwitchValid":false,"switch1Id":1,"switch1Valid":false,"switch2Id":1,"switch2Valid":false,"variableId":20,"variableValid":true,"variableValue":4},"directionFix":false,"image":{"tileId":107,"characterName":"","characterIndex":0,"direction":2,"pattern":0},"list":[{"code":101,"indent":0,"parameters":["",0,1,2]},{"code":401,"indent":0,"parameters":["这一团碎掉的东西好像曾经是一台电脑，但现在已经被摔得"]},{"code":401,"indent":0,"parameters":["不成样子了。"]},{"code":0,"indent":0,"parameters":[]}],"moveFrequency":3,"moveRoute":{"list":[{"code":0,"parameters":[]}],"repeat":true,"skippable":false,"wait":false},"moveSpeed":3,"moveType":0,"priorityType":1,"stepAnime":false,"through":false,"trigger":0,"walkAnime":true}],"x":3,"y":3},
{"id":3,"name":"EV003","note":"","pages":[{"conditions":{"actorId":1,"actorValid":false,"itemId":1,"itemValid":false,"selfSwitchCh":"A","selfSwitchValid":false,"switch1Id":1,"switch1Valid":false,"switch2Id":1,"switch2Valid":false,"variableId":1,"variableValid":false,"variableValue":0},"directionFix":false,"image":{"characterIndex":0,"characterName":"","direction":2,"pattern":0,"tileId":0},"list":[{"code":111,"indent":0,"parameters":[0,4,0]},{"code":101,"indent":1,"parameters":["",0,1,2]},{"code":401,"indent":1,"parameters":["我应该先去接电话。"]},{"code":0,"indent":1,"parameters":[]},{"code":411,"indent":0,"parameters":[]},{"code":111,"indent":1,"parameters":[6,-1,8]},{"code":101,"indent":2,"parameters":["",0,1,2]},{"code":401,"indent":2,"parameters":["这是高中很常见的一种小板报，但实际上除了每次张贴"]},{"code":401,"indent":2,"parameters":["成绩和排名的时候，并没有人会看。"]},{"code":0,"indent":2,"parameters":[]},{"code":412,"indent":1,"parameters":[]},{"code":0,"indent":1,"parameters":[]},{"code":412,"indent":0,"parameters":[]},{"code":0,"indent":0,"parameters":[]}],"moveFrequency":3,"moveRoute":{"list":[{"code":0,"parameters":[]}],"repeat":true,"skippable":false,"wait":false},"moveSpeed":3,"moveType":0,"priorityType":1,"stepAnime":false,"through":false,"trigger":0,"walkAnime":true},{"conditions":{"actorId":1,"actorValid":false,"itemId":1,"itemValid":false,"selfSwitchCh":"A","selfSwitchValid":false,"switch1Id":5,"switch1Valid":true,"switch2Id":1,"switch2Valid":false,"variableId":1,"variableValid":false,"variableValue":0},"directionFix":false,"image":{"characterIndex":0,"characterName":"","direction":2,"pattern":0,"tileId":0},"list":[{"code":111,"indent":0,"parameters":[0,4,0]},{"code":101,"indent":1,"parameters":["",0,1,2]},{"code":401,"indent":1,"parameters":["我应该先去接电话。"]},{"code":0,"indent":1,"parameters":[]},{"code":411,"indent":0,"parameters":[]},{"code":111,"indent":1,"parameters":[6,-1,8]},{"code":111,"indent":2,"parameters":[6,-1,8]},{"code":101,"indent":3,"parameters":["",0,1,2]},{"code":401,"indent":3,"parameters":["板报似乎变了样子，上面贴着几则怪异的新闻："]},{"code":101,"indent":3,"parameters":["",0,1,2]},{"code":401,"indent":3,"parameters":["2015年2月："]},{"code":401,"indent":3,"parameters":["一位中学女教师被发现死于自己床上，警方初步认为是窒息"]},{"code":401,"indent":3,"parameters":["身亡，怀疑为他杀。"]},{"code":101,"indent":3,"parameters":["",0,1,2]},{"code":401,"indent":3,"parameters":["2015年3月："]},{"code":401,"indent":3,"parameters":["又一中学女教师被发现死于教室之中，被发现时身上有三处"]},{"code":401,"indent":3,"parameters":["刀伤，警方仍在调查中。"]},{"code":101,"indent":3,"parameters":["",0,1,2]},{"code":401,"indent":3,"parameters":["2015年5月："]},{"code":401,"indent":3,"parameters":["中学男教师跳楼身亡，半年以内该校已经发生三起教师不明"]},{"code":401,"indent":3,"parameters":["死亡案件，其余教师和家长人心惶惶。"]},{"code":0,"indent":3,"parameters":[]},{"code":412,"indent":2,"parameters":[]},{"code":0,"indent":2,"parameters":[]},{"code":412,"indent":1,"parameters":[]},{"code":0,"indent":1,"parameters":[]},{"code":412,"indent":0,"parameters":[]},{"code":0,"indent":0,"parameters":[]}],"moveFrequency":3,"moveRoute":{"list":[{"code":0,"parameters":[]}],"repeat":true,"skippable":false,"wait":false},"moveSpeed":3,"moveType":0,"priorityType":1,"stepAnime":false,"through":false,"trigger":0,"walkAnime":true},{"conditions":{"actorId":1,"actorValid":false,"itemId":1,"itemValid":false,"selfSwitchCh":"A","selfSwitchValid":false,"switch1Id":1,"switch1Valid":false,"switch2Id":1,"switch2Valid":false,"variableId":20,"variableValid":true,"variableValue":4},"directionFix":false,"image":{"characterIndex":0,"characterName":"","direction":2,"pattern":0,"tileId":0},"list":[{"code":101,"indent":0,"parameters":["",0,1,2]},{"code":401,"indent":0,"parameters":["版报上贴着很多纸，但它们都是空的。"]},{"code":0,"indent":0,"parameters":[]}],"moveFrequency":3,"moveRoute":{"list":[{"code":0,"parameters":[]}],"repeat":true,"skippable":false,"wait":false},"moveSpeed":3,"moveType":0,"priorityType":1,"stepAnime":false,"through":false,"trigger":0,"walkAnime":true}],"x":9,"y":1},
{"id":4,"name":"EV004","note":"","pages":[{"conditions":{"actorId":1,"actorValid":false,"itemId":1,"itemValid":false,"selfSwitchCh":"A","selfSwitchValid":false,"switch1Id":1,"switch1Valid":false,"switch2Id":1,"switch2Valid":false,"variableId":1,"variableValid":false,"variableValue":0},"directionFix":true,"image":{"characterIndex":7,"characterName":"!Chest","direction":2,"pattern":1,"tileId":0},"list":[{"code":111,"indent":0,"parameters":[0,4,0]},{"code":101,"indent":1,"parameters":["",0,1,2]},{"code":401,"indent":1,"parameters":["我应该先去接电话。"]},{"code":0,"indent":1,"parameters":[]},{"code":411,"indent":0,"parameters":[]},{"code":101,"indent":1,"parameters":["",0,1,2]},{"code":401,"indent":1,"parameters":["一个上着密码的箱子，下面署名写着高毅。"]},{"code":101,"indent":1,"parameters":["",0,1,2]},{"code":401,"indent":1,"parameters":["输一个密码试试看："]},{"code":103,"indent":1,"parameters":[4,8]},{"code":111,"indent":1,"parameters":[1,4,0,19621213,0]},{"code":250,"indent":2,"parameters":[{"name":"Chest1","pan":0,"pitch":100,"volume":90}]},{"code":205,"indent":2,"parameters":[0,{"list":[{"code":36},{"code":17},{"code":15,"parameters":[3]},{"code":18},{"code":15,"parameters":[3]},{"code":0}],"repeat":false,"skippable":false,"wait":true}]},{"code":505,"indent":2,"parameters":[{"code":36}]},{"code":505,"indent":2,"parameters":[{"code":17}]},{"code":505,"indent":2,"parameters":[{"code":15,"parameters":[3]}]},{"code":505,"indent":2,"parameters":[{"code":18}]},{"code":505,"indent":2,"parameters":[{"code":15,"parameters":[3]}]},{"code":123,"indent":2,"parameters":["A",0]},{"code":126,"indent":2,"parameters":[2,0,0,1]},{"code":101,"indent":2,"parameters":["",0,1,2]},{"code":401,"indent":2,"parameters":["获得：一块手帕。"]},{"code":0,"indent":2,"parameters":[]},{"code":411,"indent":1,"parameters":[]},{"code":101,"indent":2,"parameters":["",0,1,2]},{"code":401,"indent":2,"parameters":["什么都没有发生。"]},{"code":0,"indent":2,"parameters":[]},{"code":412,"indent":1,"parameters":[]},{"code":0,"indent":1,"parameters":[]},{"code":412,"indent":0,"parameters":[]},{"code":0,"indent":0,"parameters":[]}],"moveFrequency":3,"moveRoute":{"list":[{"code":0,"parameters":[]}],"repeat":true,"skippable":false,"wait":false},"moveSpeed":3,"moveType":0,"priorityType":1,"stepAnime":false,"through":false,"trigger":0,"walkAnime":false},{"conditions":{"actorId":1,"actorValid":false,"itemId":1,"itemValid":false,"selfSwitchCh":"A","selfSwitchValid":true,"switch1Id":1,"switch1Valid":false,"switch2Id":1,"switch2Valid":false,"variableId":1,"variableValid":false,"variableValue":0},"directionFix":true,"image":{"characterIndex":7,"characterName":"!Chest","direction":8,"pattern":1,"tileId":0},"list":[{"code":0,"indent":0,"parameters":[]}],"moveFrequency":3,"moveRoute":{"list":[{"code":0,"parameters":[]}],"repeat":true,"skippable":false,"wait":false},"moveSpeed":3,"moveType":0,"priorityType":1,"stepAnime":false,"through":false,"trigger":0,"walkAnime":false},{"conditions":{"actorId":1,"actorValid":false,"itemId":1,"itemValid":false,"selfSwitchCh":"A","selfSwitchValid":false,"switch1Id":1,"switch1Valid":false,"switch2Id":1,"switch2Valid":false,"variableId":20,"variableValid":true,"variableValue":4},"directionFix":false,"image":{"characterIndex":0,"characterName":"","direction":2,"pattern":0,"tileId":0},"list":[{"code":0,"indent":0,"parameters":[]}],"moveFrequency":3,"moveRoute":{"list":[{"code":0,"parameters":[]}],"repeat":true,"skippable":false,"wait":false},"moveSpeed":3,"moveType":0,"priorityType":1,"stepAnime":false,"through":false,"trigger":0,"walkAnime":true}],"x":10,"y":5},
{"id":5,"name":"EV005","note":"","pages":[{"conditions":{"actorId":1,"actorValid":false,"itemId":1,"itemValid":false,"selfSwitchCh":"A","selfSwitchValid":false,"switch1Id":4,"switch1Valid":true,"switch2Id":1,"switch2Valid":false,"variableId":1,"variableValid":false,"variableValue":0},"directionFix":false,"image":{"characterIndex":0,"characterName":"","direction":2,"pattern":0,"tileId":0},"list":[{"code":112,"indent":0,"parameters":[]},{"code":230,"indent":1,"parameters":[120]},{"code":250,"indent":1,"parameters":[{"name":"Phone","volume":90,"pitch":100,"pan":0}]},{"code":111,"indent":1,"parameters":[0,4,1]},{"code":113,"indent":2,"parameters":[]},{"code":0,"indent":2,"parameters":[]},{"code":412,"indent":1,"parameters":[]},{"code":0,"indent":1,"parameters":[]},{"code":413,"indent":0,"parameters":[]},{"code":0,"indent":0,"parameters":[]}],"moveFrequency":3,"moveRoute":{"list":[{"code":0,"parameters":[]}],"repeat":true,"skippable":false,"wait":false},"moveSpeed":3,"moveType":0,"priorityType":0,"stepAnime":false,"through":false,"trigger":4,"walkAnime":true}],"x":0,"y":0},
{"id":6,"name":"EV006","note":"","pages":[{"conditions":{"actorId":1,"actorValid":false,"itemId":1,"itemValid":false,"selfSwitchCh":"A","selfSwitchValid":false,"switch1Id":8,"switch1Valid":false,"switch2Id":1,"switch2Valid":false,"variableId":1,"variableValid":false,"variableValue":0},"directionFix":false,"image":{"tileId":432,"characterName":"","characterIndex":0,"direction":2,"pattern":0},"list":[{"code":111,"indent":0,"parameters":[0,4,0]},{"code":101,"indent":1,"parameters":["",0,1,2]},{"code":401,"indent":1,"parameters":["我应该先去接电话。"]},{"code":0,"indent":1,"parameters":[]},{"code":411,"indent":0,"parameters":[]},{"code":101,"indent":1,"parameters":["",0,1,2]},{"code":401,"indent":1,"parameters":["地上放着一本《化学试剂大全》，被人翻的太多，已经破损"]},{"code":401,"indent":1,"parameters":["严重。"]},{"code":123,"indent":1,"parameters":["A",0]},{"code":0,"indent":1,"parameters":[]},{"code":412,"indent":0,"parameters":[]},{"code":0,"indent":0,"parameters":[]}],"moveFrequency":3,"moveRoute":{"list":[{"code":0,"parameters":[]}],"repeat":true,"skippable":false,"wait":false},"moveSpeed":3,"moveType":0,"priorityType":1,"stepAnime":false,"through":false,"trigger":0,"walkAnime":true},{"conditions":{"actorId":1,"actorValid":false,"itemId":1,"itemValid":false,"selfSwitchCh":"A","selfSwitchValid":false,"switch1Id":8,"switch1Valid":true,"switch2Id":1,"switch2Valid":false,"variableId":1,"variableValid":false,"variableValue":0},"directionFix":false,"image":{"tileId":432,"characterName":"","characterIndex":0,"direction":2,"pattern":0},"list":[{"code":111,"indent":0,"parameters":[0,4,0]},{"code":101,"indent":1,"parameters":["",0,1,2]},{"code":401,"indent":1,"parameters":["我应该先去接电话。"]},{"code":0,"indent":1,"parameters":[]},{"code":411,"indent":0,"parameters":[]},{"code":111,"indent":1,"parameters":[2,"A",1]},{"code":101,"indent":2,"parameters":["",0,1,2]},{"code":401,"indent":2,"parameters":["地上放着一本《化学试剂大全》，被人翻的太多，已经破损"]},{"code":401,"indent":2,"parameters":["严重。"]},{"code":123,"indent":2,"parameters":["A",0]},{"code":0,"indent":2,"parameters":[]},{"code":412,"indent":1,"parameters":[]},{"code":101,"indent":1,"parameters":["",0,1,2]},{"code":401,"indent":1,"parameters":["要试着找什么东西吗？"]},{"code":112,"indent":1,"parameters":[]},{"code":102,"indent":2,"parameters":[["硫酸铜溶液","氯化铁溶液","高锰酸钾溶液","铁氰化钾粉末","离开"],-1,-1,2,0]},{"code":402,"indent":2,"parameters":[0,"硫酸铜溶液"]},{"code":101,"indent":3,"parameters":["",0,1,2]},{"code":401,"indent":3,"parameters":["硫酸铜溶液为蓝色液体。"]},{"code":0,"indent":3,"parameters":[]},{"code":402,"indent":2,"parameters":[1,"氯化铁溶液"]},{"code":101,"indent":3,"parameters":["",0,1,2]},{"code":401,"indent":3,"parameters":["氯化铁溶液为黄色液体。"]},{"code":0,"indent":3,"parameters":[]},{"code":402,"indent":2,"parameters":[2,"高锰酸钾溶液"]},{"code":101,"indent":3,"parameters":["",0,1,2]},{"code":401,"indent":3,"parameters":["高锰酸钾溶液为紫色液体。"]},{"code":0,"indent":3,"parameters":[]},{"code":402,"indent":2,"parameters":[3,"铁氰化钾粉末"]},{"code":101,"indent":3,"parameters":["",0,1,2]},{"code":401,"indent":3,"parameters":["铁氰化钾是一种较为复杂的络合物，呈现\\C[18]血红色\\C[0]。"]},{"code":101,"indent":3,"parameters":["",0,1,2]},{"code":401,"indent":3,"parameters":["\"血红色“这三个字被血渍染红了。"]},{"code":0,"indent":3,"parameters":[]},{"code":402,"indent":2,"parameters":[4,"离开"]},{"code":113,"indent":3,"parameters":[]},{"code":0,"indent":3,"parameters":[]},{"code":404,"indent":2,"parameters":[]},{"code":0,"indent":2,"parameters":[]},{"code":413,"indent":1,"parameters":[]},{"code":123,"indent":1,"parameters":["A",0]},{"code":0,"indent":1,"parameters":[]},{"code":412,"indent":0,"parameters":[]},{"code":0,"indent":0,"parameters":[]}],"moveFrequency":3,"moveRoute":{"list":[{"code":0,"parameters":[]}],"repeat":true,"skippable":false,"wait":false},"moveSpeed":3,"moveType":0,"priorityType":1,"stepAnime":false,"through":false,"trigger":0,"walkAnime":true},{"conditions":{"actorId":1,"actorValid":false,"itemId":1,"itemValid":false,"selfSwitchCh":"A","selfSwitchValid":false,"switch1Id":1,"switch1Valid":false,"switch2Id":1,"switch2Valid":false,"variableId":20,"variableValid":true,"variableValue":4},"directionFix":false,"image":{"characterIndex":0,"characterName":"","direction":2,"pattern":0,"tileId":0},"list":[{"code":0,"indent":0,"parameters":[]}],"moveFrequency":3,"moveRoute":{"list":[{"code":0,"parameters":[]}],"repeat":true,"skippable":false,"wait":false},"moveSpeed":3,"moveType":0,"priorityType":0,"stepAnime":false,"through":false,"trigger":0,"walkAnime":true}],"x":7,"y":3},
{"id":7,"name":"EV007","note":"","pages":[{"conditions":{"actorId":1,"actorValid":false,"itemId":1,"itemValid":false,"selfSwitchCh":"A","selfSwitchValid":false,"switch1Id":5,"switch1Valid":false,"switch2Id":1,"switch2Valid":false,"variableId":1,"variableValid":false,"variableValue":0},"directionFix":false,"image":{"tileId":0,"characterName":"","direction":6,"pattern":0,"characterIndex":4},"list":[{"code":101,"indent":0,"parameters":["",0,1,2]},{"code":401,"indent":0,"parameters":["今日趣味谜题-编号20201206："]},{"code":401,"indent":0,"parameters":["高老师一家三口年龄加起来是141岁，师母比高老师小两岁，"]},{"code":401,"indent":0,"parameters":["四年之后，高老师的年龄是他儿子的两倍，请问高老师今年"]},{"code":401,"indent":0,"parameters":["多大呢？"]},{"code":0,"indent":0,"parameters":[]}],"moveFrequency":3,"moveRoute":{"list":[{"code":0,"parameters":[]}],"repeat":true,"skippable":false,"wait":false},"moveSpeed":3,"moveType":0,"priorityType":1,"stepAnime":false,"through":false,"trigger":0,"walkAnime":true},{"conditions":{"actorId":1,"actorValid":false,"itemId":1,"itemValid":false,"selfSwitchCh":"A","selfSwitchValid":false,"switch1Id":1,"switch1Valid":false,"switch2Id":1,"switch2Valid":false,"variableId":20,"variableValid":true,"variableValue":4},"directionFix":false,"image":{"characterIndex":0,"characterName":"","direction":2,"pattern":0,"tileId":0},"list":[{"code":101,"indent":0,"parameters":["",0,1,2]},{"code":401,"indent":0,"parameters":["一张纸条，上面写着："]},{"code":401,"indent":0,"parameters":["“生命轮回之必需品："]},{"code":401,"indent":0,"parameters":["  生命之始，生命之窗，生命之柱，生命之律。”"]},{"code":0,"indent":0,"parameters":[]}],"moveFrequency":3,"moveRoute":{"list":[{"code":0,"parameters":[]}],"repeat":true,"skippable":false,"wait":false},"moveSpeed":3,"moveType":0,"priorityType":1,"stepAnime":false,"through":false,"trigger":0,"walkAnime":true}],"x":8,"y":1},
{"id":8,"name":"EV008","note":"","pages":[{"conditions":{"actorId":1,"actorValid":false,"itemId":1,"itemValid":false,"selfSwitchCh":"A","selfSwitchValid":false,"switch1Id":1,"switch1Valid":false,"switch2Id":5,"switch2Valid":true,"variableId":1,"variableValid":false,"variableValue":0},"directionFix":false,"image":{"tileId":125,"characterName":"","characterIndex":0,"direction":2,"pattern":0},"list":[{"code":111,"indent":0,"parameters":[0,4,0]},{"code":101,"indent":1,"parameters":["",0,1,2]},{"code":401,"indent":1,"parameters":["我应该先去接电话。"]},{"code":0,"indent":1,"parameters":[]},{"code":411,"indent":0,"parameters":[]},{"code":101,"indent":1,"parameters":["",0,1,2]},{"code":401,"indent":1,"parameters":["在教室里摆放着一些化学试剂，贴着标签，但都是空的。"]},{"code":401,"indent":1,"parameters":["从左到右分别是："]},{"code":401,"indent":1,"parameters":["硫酸铜溶液，氯化铁溶液，高锰酸钾溶液，铁氰化钾粉末"]},{"code":121,"indent":1,"parameters":[8,8,0]},{"code":0,"indent":1,"parameters":[]},{"code":412,"indent":0,"parameters":[]},{"code":0,"indent":0,"parameters":[]}],"moveFrequency":3,"moveRoute":{"list":[{"code":0,"parameters":[]}],"repeat":true,"skippable":false,"wait":false},"moveSpeed":3,"moveType":0,"priorityType":1,"stepAnime":false,"through":false,"trigger":0,"walkAnime":true},{"conditions":{"actorId":1,"actorValid":false,"itemId":1,"itemValid":false,"selfSwitchCh":"A","selfSwitchValid":false,"switch1Id":1,"switch1Valid":false,"switch2Id":5,"switch2Valid":false,"variableId":20,"variableValid":true,"variableValue":4},"directionFix":false,"image":{"tileId":0,"characterName":"","direction":2,"pattern":2,"characterIndex":5},"list":[{"code":0,"indent":0,"parameters":[]}],"moveFrequency":3,"moveRoute":{"list":[{"code":0,"parameters":[]}],"repeat":true,"skippable":false,"wait":false},"moveSpeed":3,"moveType":0,"priorityType":1,"stepAnime":false,"through":false,"trigger":0,"walkAnime":true}],"x":9,"y":3},
{"id":9,"name":"EV009","note":"","pages":[{"conditions":{"actorId":1,"actorValid":false,"itemId":1,"itemValid":false,"selfSwitchCh":"A","selfSwitchValid":false,"switch1Id":5,"switch1Valid":false,"switch2Id":1,"switch2Valid":false,"variableId":1,"variableValid":false,"variableValue":0},"directionFix":false,"image":{"tileId":0,"characterName":"People1","direction":2,"pattern":1,"characterIndex":6},"list":[{"code":111,"indent":0,"parameters":[0,7,1]},{"code":101,"indent":1,"parameters":["",0,1,2]},{"code":401,"indent":1,"parameters":["站在这里的是我们当时的一个年级主任，姓王。"]},{"code":101,"indent":1,"parameters":["People1",6,1,2]},{"code":401,"indent":1,"parameters":["【王主任】"]},{"code":401,"indent":1,"parameters":["你是哪来的？！"]},{"code":101,"indent":1,"parameters":["People1",6,1,2]},{"code":401,"indent":1,"parameters":["【王主任】"]},{"code":401,"indent":1,"parameters":["门卫怎么就把你放进来？！"]},{"code":101,"indent":1,"parameters":["Actor1",5,1,2]},{"code":401,"indent":1,"parameters":["【小德（我）】"]},{"code":401,"indent":1,"parameters":["老师我是来帮……"]},{"code":101,"indent":1,"parameters":["People1",6,1,2]},{"code":401,"indent":1,"parameters":["【王主任】"]},{"code":401,"indent":1,"parameters":["学校里不欢迎你这样的人，你会把学校搞乱的。"]},{"code":101,"indent":1,"parameters":["People1",6,1,2]},{"code":401,"indent":1,"parameters":["【王主任】"]},{"code":401,"indent":1,"parameters":["\\.快!\\.滚！"]},{"code":101,"indent":1,"parameters":["",0,1,2]},{"code":401,"indent":1,"parameters":["当时上学的时候他就不太讲道理，没想到还是没变。"]},{"code":401,"indent":1,"parameters":["或许我该去找找别人。"]},{"code":121,"indent":1,"parameters":[7,7,0]},{"code":0,"indent":1,"parameters":[]},{"code":411,"indent":0,"parameters":[]},{"code":101,"indent":1,"parameters":["People1",6,1,2]},{"code":401,"indent":1,"parameters":["【王主任】"]},{"code":401,"indent":1,"parameters":["你要是再不走我就要叫保安了！"]},{"code":101,"indent":1,"parameters":["",0,1,2]},{"code":401,"indent":1,"parameters":["我不该跟不讲道理的人说话，我或许可以去找找别人。"]},{"code":0,"indent":1,"parameters":[]},{"code":412,"indent":0,"parameters":[]},{"code":0,"indent":0,"parameters":[]}],"moveFrequency":3,"moveRoute":{"list":[{"code":0,"parameters":[]}],"repeat":true,"skippable":false,"wait":false},"moveSpeed":3,"moveType":0,"priorityType":1,"stepAnime":false,"through":false,"trigger":0,"walkAnime":false},{"conditions":{"actorId":1,"actorValid":false,"itemId":1,"itemValid":false,"selfSwitchCh":"A","selfSwitchValid":false,"switch1Id":5,"switch1Valid":true,"switch2Id":1,"switch2Valid":false,"variableId":1,"variableValid":false,"variableValue":0},"directionFix":false,"image":{"tileId":439,"characterName":"","characterIndex":0,"direction":2,"pattern":0},"list":[{"code":111,"indent":0,"parameters":[0,4,0]},{"code":101,"indent":1,"parameters":["",0,1,2]},{"code":401,"indent":1,"parameters":["我应该先去接电话。"]},{"code":0,"indent":1,"parameters":[]},{"code":411,"indent":0,"parameters":[]},{"code":101,"indent":1,"parameters":["",0,1,2]},{"code":401,"indent":1,"parameters":["已经多处破损的蓝色熊玩偶，僵硬地倒在教室里，身上被破开"]},{"code":401,"indent":1,"parameters":["了三个口子，一幅图画从破口处掉了出来。"]},{"code":231,"indent":1,"parameters":[1,"water2",0,0,5,4,40,40,255,0]},{"code":230,"indent":1,"parameters":[240]},{"code":235,"indent":1,"parameters":[1]},{"code":0,"indent":1,"parameters":[]},{"code":412,"indent":0,"parameters":[]},{"code":0,"indent":0,"parameters":[]}],"moveFrequency":3,"moveRoute":{"list":[{"code":0,"parameters":[]}],"repeat":true,"skippable":false,"wait":false},"moveSpeed":3,"moveType":0,"priorityType":1,"stepAnime":false,"through":false,"trigger":0,"walkAnime":true},{"conditions":{"actorId":1,"actorValid":false,"itemId":1,"itemValid":false,"selfSwitchCh":"A","selfSwitchValid":false,"switch1Id":1,"switch1Valid":false,"switch2Id":1,"switch2Valid":false,"variableId":20,"variableValid":true,"variableValue":4},"directionFix":false,"image":{"characterIndex":0,"characterName":"","direction":2,"pattern":0,"tileId":0},"list":[{"code":0,"indent":0,"parameters":[]}],"moveFrequency":3,"moveRoute":{"list":[{"code":0,"parameters":[]}],"repeat":true,"skippable":false,"wait":false},"moveSpeed":3,"moveType":0,"priorityType":0,"stepAnime":false,"through":false,"trigger":0,"walkAnime":true}],"x":5,"y":6},
{"id":10,"name":"EV010","note":"","pages":[{"conditions":{"actorId":1,"actorValid":false,"itemId":1,"itemValid":false,"selfSwitchCh":"A","selfSwitchValid":false,"switch1Id":5,"switch1Valid":true,"switch2Id":1,"switch2Valid":false,"variableId":1,"variableValid":false,"variableValue":0},"directionFix":false,"image":{"tileId":341,"characterName":"","characterIndex":0,"direction":2,"pattern":0},"list":[{"code":0,"indent":0,"parameters":[]}],"moveFrequency":3,"moveRoute":{"list":[{"code":0,"parameters":[]}],"repeat":true,"skippable":false,"wait":false},"moveSpeed":3,"moveType":0,"priorityType":0,"stepAnime":false,"through":false,"trigger":0,"walkAnime":true},{"conditions":{"actorId":1,"actorValid":false,"itemId":1,"itemValid":false,"selfSwitchCh":"A","selfSwitchValid":false,"switch1Id":1,"switch1Valid":false,"switch2Id":1,"switch2Valid":false,"variableId":20,"variableValid":true,"variableValue":4},"directionFix":false,"image":{"characterIndex":0,"characterName":"","direction":2,"pattern":0,"tileId":0},"list":[{"code":0,"indent":0,"parameters":[]}],"moveFrequency":3,"moveRoute":{"list":[{"code":0,"parameters":[]}],"repeat":true,"skippable":false,"wait":false},"moveSpeed":3,"moveType":0,"priorityType":0,"stepAnime":false,"through":false,"trigger":0,"walkAnime":true}],"x":6,"y":6}
]
}